fast_crossing/__init__.py
fast_crossing/_core.cpython-39-x86_64-linux-gnu.so
fast_crossing/py.typed
fast_crossing/spatial.py
fast_crossing/_core/__init__.pyi
fast_crossing/_core/tf.pyi
fast_crossing/cli/__init__.py
fast_crossing-0.1.2.dist-info/METADATA
fast_crossing-0.1.2.dist-info/WHEEL
fast_crossing-0.1.2.dist-info/RECORD
fast_crossing-0.1.2.dist-info/licenses/LICENSE
